plover_auto_reconnect_machine.py
plover_auto_reconnect_machine-0.1.0.dist-info/LICENSE
plover_auto_reconnect_machine-0.1.0.dist-info/METADATA
plover_auto_reconnect_machine-0.1.0.dist-info/WHEEL
plover_auto_reconnect_machine-0.1.0.dist-info/entry_points.txt
plover_auto_reconnect_machine-0.1.0.dist-info/top_level.txt
plover_auto_reconnect_machine-0.1.0.dist-info/zip-safe
plover_auto_reconnect_machine-0.1.0.dist-info/RECORD
