Metadata-Version: 2.1
Name: plover-auto-reconnect-machine
Version: 0.1.0
Summary: This extension tries to automatically reconnect the steno machine if the connection got lost.
Home-page: https://github.com/tschulte/plover_auto_reconnect_machine
Author: Tobias Schulte
Author-email: tobias.schulte@gliderpilot.de
License: GNU General Public License v3 or later (GPLv3+)
Keywords: plover plover_plugin
Classifier: Development Status :: 4 - Beta
Classifier: Environment :: Plugins
Classifier: Intended Audience :: End Users/Desktop
Classifier: License :: OSI Approved :: GNU General Public License v3 or later (GPLv3+)
Classifier: Operating System :: OS Independent
Classifier: Programming Language :: Python :: 3
Classifier: Programming Language :: Python :: 3.6
License-File: LICENSE
Requires-Dist: plover >=4.0.0rc2
